{
	"id": "nodebb-theme-fusionauth",
	"library": "./lib/theme.js",
	"hooks": [
		{ "hook": "filter:widgets.getAreas", "method": "defineWidgetAreas" },
		{ "hook": "filter:config.get", "method": "getThemeConfig" },
		{ "hook": "static:app.load", "method": "init" },
		{ "hook": "filter:admin.header.build", "method": "addAdminNavigation" },
		{ "hook": "filter:user.profileMenu", "method": "addProfileItem" }
	],
	"scripts": [
		"../nodebb-theme-persona/public/modules/autohidingnavbar.js",
		"../nodebb-theme-persona/public/persona.js"
	],
	"templates": "templates",
	"modules": {
		"../admin/plugins/persona.js": "../nodebb-theme-persona/public/admin.js",
		"persona/taskbar.js": "../nodebb-theme-persona/public/modules/taskbar.js",
		"persona/mobile-menu.js": "../nodebb-theme-persona/public/modules/mobile-menu.js",
		"../client/account/theme.js": "../nodebb-theme-persona/public/settings.js"
	}
}
